<?xml version='1.0' encoding='utf-8' standalone='yes'?>
<collection>
  <source>Ocean-Certain Corpus</source>
  <date>2017-03-14</date>
  <key></key>
  <infon key="part">abs1</infon>
  <document>
    <id>10.1038#nature11533#abs#sent#bioc#annot</id>
    <infon key="bibtex">
 @article{Deegan_2012, title={Coastal eutrophication as a driver of salt marsh loss}, volume={490}, ISSN={1476-4687}, url={http://dx.doi.org/10.1038/nature11533}, DOI={10.1038/nature11533}, number={7420}, journal={Nature}, publisher={Nature Publishing Group}, author={Deegan, Linda A. and Johnson, David Samuel and Warren, R. Scott and Peterson, Bruce J. and Fleeger, John W. and Fagherazzi, Sergio and Wollheim, Wilfred M.}, year={2012}, month={Oct}, pages={388–392}}
</infon>
    <infon key="source">http://dx.doi.org/data/brat/abs1/10.1038/nature11533</infon>
    <passage>
      <offset>0</offset>
      <infon key="type">title</infon>
      <sentence>
        <infon key="n">1</infon>
        <offset>0</offset>
        <text>Coastal eutrophication as a driver of salt marsh loss
</text>
        <annotation id="T1">
          <infon key="brat-id">T1</infon>
          <infon key="type">Decrease</infon>
          <infon key="brat-type">text-bound</infon>
          <location length="4" offset="49"/>
          <text>loss</text>
        </annotation>
        <annotation id="T2">
          <infon key="brat-id">T2</infon>
          <infon key="type">Variable</infon>
          <infon key="brat-type">text-bound</infon>
          <location length="10" offset="38"/>
          <text>salt marsh</text>
        </annotation>
        <annotation id="T3">
          <infon key="brat-id">T3</infon>
          <infon key="type">Cause</infon>
          <infon key="brat-type">text-bound</infon>
          <location length="9" offset="28"/>
          <text>driver of</text>
        </annotation>
        <annotation id="T30">
          <infon key="brat-id">T30</infon>
          <infon key="type">I_Change</infon>
          <infon key="brat-type">text-bound</infon>
          <location length="14" offset="8"/>
          <text>eutrophication</text>
        </annotation>
        <relation id="E1">
          <infon key="brat-id">E1</infon>
          <infon key="type">Decrease</infon>
          <infon key="brat-type">event</infon>
          <node refid="T1" role="Decrease"/>
          <node refid="T2" role="Theme"/>
        </relation>
        <relation id="E2">
          <infon key="brat-id">E2</infon>
          <infon key="type">Cause</infon>
          <infon key="brat-type">event</infon>
          <node refid="T3" role="Cause"/>
          <node refid="E16" role="Agent"/>
          <node refid="E1" role="Theme"/>
        </relation>
        <relation id="E16">
          <infon key="brat-id">E16</infon>
          <infon key="type">I_Change</infon>
          <infon key="brat-type">event</infon>
          <node refid="T30" role="I_Change"/>
        </relation>
      </sentence>
    </passage>
    <passage>
      <offset>54</offset>
      <infon key="type">body</infon>
      <sentence>
        <infon key="n">2</infon>
        <offset>54</offset>
        <text>Salt marshes are highly productive coastal wetlands that provide important ecosystem services such as storm protection for coastal cities, nutrient removal and carbon sequestration.
</text>
        <annotation id="T4">
          <infon key="brat-id">T4</infon>
          <infon key="type">Decrease</infon>
          <infon key="brat-type">text-bound</infon>
          <location length="7" offset="202"/>
          <text>removal</text>
        </annotation>
        <annotation id="T5">
          <infon key="brat-id">T5</infon>
          <infon key="type">Variable</infon>
          <infon key="brat-type">text-bound</infon>
          <location length="8" offset="193"/>
          <text>nutrient</text>
        </annotation>
        <relation id="E3">
          <infon key="brat-id">E3</infon>
          <infon key="type">Decrease</infon>
          <infon key="brat-type">event</infon>
          <node refid="T4" role="Decrease"/>
          <node refid="T5" role="Theme"/>
        </relation>
      </sentence>
      <sentence>
        <infon key="n">3</infon>
        <offset>236</offset>
        <text>Despite protective measures, however, worldwide losses of these ecosystems have accelerated in recent decades.
</text>
      </sentence>
      <sentence>
        <infon key="n">4</infon>
        <offset>347</offset>
        <text>Here we present data from a nine-year whole-ecosystem nutrient-enrichment experiment.
</text>
      </sentence>
      <sentence>
        <infon key="n">5</infon>
        <offset>433</offset>
        <text>Our study demonstrates that nutrient enrichment, a global problem for coastal ecosystems, can be a driver of salt marsh loss.
</text>
        <annotation id="T7">
          <infon key="brat-id">T7</infon>
          <infon key="type">Decrease</infon>
          <infon key="brat-type">text-bound</infon>
          <location length="4" offset="553"/>
          <text>loss</text>
        </annotation>
        <annotation id="T8">
          <infon key="brat-id">T8</infon>
          <infon key="type">Variable</infon>
          <infon key="brat-type">text-bound</infon>
          <location length="10" offset="542"/>
          <text>salt marsh</text>
        </annotation>
        <relation id="E5">
          <infon key="brat-id">E5</infon>
          <infon key="type">Decrease</infon>
          <infon key="brat-type">event</infon>
          <node refid="T7" role="Decrease"/>
          <node refid="T8" role="Theme"/>
        </relation>
      </sentence>
      <sentence>
        <infon key="n">6</infon>
        <offset>559</offset>
        <text>We show that nutrient levels commonly associated with coastal eutrophication increased above-ground leaf biomass, decreased the dense, below-ground biomass of bank-stabilizing roots, and increased microbial decomposition of organic matter.
</text>
        <annotation id="T9">
          <infon key="brat-id">T9</infon>
          <infon key="type">Decrease</infon>
          <infon key="brat-type">text-bound</infon>
          <location length="9" offset="673"/>
          <text>decreased</text>
        </annotation>
        <annotation id="T10">
          <infon key="brat-id">T10</infon>
          <infon key="type">Increase</infon>
          <infon key="brat-type">text-bound</infon>
          <location length="9" offset="636"/>
          <text>increased</text>
        </annotation>
        <annotation id="T11">
          <infon key="brat-id">T11</infon>
          <infon key="type">Variable</infon>
          <infon key="brat-type">text-bound</infon>
          <location length="25" offset="646"/>
          <text>above-ground leaf biomass</text>
        </annotation>
        <annotation id="T12">
          <infon key="brat-id">T12</infon>
          <infon key="type">Variable</infon>
          <infon key="brat-type">text-bound</infon>
          <location length="15" offset="572"/>
          <text>nutrient levels</text>
        </annotation>
        <annotation id="T13">
          <infon key="brat-id">T13</infon>
          <infon key="type">Variable</infon>
          <infon key="brat-type">text-bound</infon>
          <location length="57" offset="683"/>
          <text>the dense, below-ground biomass of bank-stabilizing roots</text>
        </annotation>
        <annotation id="T14">
          <infon key="brat-id">T14</infon>
          <infon key="type">Increase</infon>
          <infon key="brat-type">text-bound</infon>
          <location length="9" offset="746"/>
          <text>increased</text>
        </annotation>
        <annotation id="T15">
          <infon key="brat-id">T15</infon>
          <infon key="type">Variable</infon>
          <infon key="brat-type">text-bound</infon>
          <location length="41" offset="756"/>
          <text>microbial decomposition of organic matter</text>
        </annotation>
        <relation id="E6">
          <infon key="brat-id">E6</infon>
          <infon key="type">Decrease</infon>
          <infon key="brat-type">event</infon>
          <node refid="T9" role="Decrease"/>
          <node refid="T13" role="Theme"/>
        </relation>
        <relation id="E7">
          <infon key="brat-id">E7</infon>
          <infon key="type">Increase</infon>
          <infon key="brat-type">event</infon>
          <node refid="T10" role="Increase"/>
          <node refid="T11" role="Theme"/>
        </relation>
        <relation id="E8">
          <infon key="brat-id">E8</infon>
          <infon key="type">Increase</infon>
          <infon key="brat-type">event</infon>
          <node refid="T14" role="Increase"/>
          <node refid="T15" role="Theme"/>
        </relation>
      </sentence>
      <sentence>
        <infon key="n">7</infon>
        <offset>799</offset>
        <text>Alterations in these key ecosystem properties reduced geomorphic stability, resulting in creek-bank collapse with significant areas of creek-bank marsh converted to unvegetated mud.
</text>
        <annotation id="T16">
          <infon key="brat-id">T16</infon>
          <infon key="type">Decrease</infon>
          <infon key="brat-type">text-bound</infon>
          <location length="7" offset="845"/>
          <text>reduced</text>
        </annotation>
        <annotation id="T17">
          <infon key="brat-id">T17</infon>
          <infon key="type">Variable</infon>
          <infon key="brat-type">text-bound</infon>
          <location length="20" offset="853"/>
          <text>geomorphic stability</text>
        </annotation>
        <relation id="E9">
          <infon key="brat-id">E9</infon>
          <infon key="type">Decrease</infon>
          <infon key="brat-type">event</infon>
          <node refid="T16" role="Decrease"/>
          <node refid="T17" role="Theme"/>
        </relation>
      </sentence>
      <sentence>
        <infon key="n">8</infon>
        <offset>981</offset>
        <text>This pattern of marsh loss parallels observations for anthropogenically nutrient-enriched marshes worldwide, with creek-edge and bay-edge marsh evolving into mudflats and wider creeks.
</text>
      </sentence>
      <sentence>
        <infon key="n">9</infon>
        <offset>1166</offset>
        <text>Our work suggests that current nutrient loading rates to many coastal ecosystems have overwhelmed the capacity of marshes to remove nitrogen without deleterious effects.
</text>
        <annotation id="T20">
          <infon key="brat-id">T20</infon>
          <infon key="type">Decrease</infon>
          <infon key="brat-type">text-bound</infon>
          <location length="6" offset="1291"/>
          <text>remove</text>
        </annotation>
        <annotation id="T21">
          <infon key="brat-id">T21</infon>
          <infon key="type">Variable</infon>
          <infon key="brat-type">text-bound</infon>
          <location length="8" offset="1298"/>
          <text>nitrogen</text>
        </annotation>
        <relation id="E11">
          <infon key="brat-id">E11</infon>
          <infon key="type">Decrease</infon>
          <infon key="brat-type">event</infon>
          <node refid="T20" role="Decrease"/>
          <node refid="T21" role="Theme"/>
        </relation>
      </sentence>
      <sentence>
        <infon key="n">10</infon>
        <offset>1336</offset>
        <text>Projected increases in nitrogen flux to the coast, related to increased fertilizer use required to feed an expanding human population, may rapidly result in a coastal landscape with less marsh, which would reduce the capacity of coastal regions to provide important ecological and economic services.
</text>
        <annotation id="T22">
          <infon key="brat-id">T22</infon>
          <infon key="type">Increase</infon>
          <infon key="brat-type">text-bound</infon>
          <location length="9" offset="1346"/>
          <text>increases</text>
        </annotation>
        <annotation id="T23">
          <infon key="brat-id">T23</infon>
          <infon key="type">Variable</infon>
          <infon key="brat-type">text-bound</infon>
          <location length="26" offset="1359"/>
          <text>nitrogen flux to the coast</text>
        </annotation>
        <annotation id="T24">
          <infon key="brat-id">T24</infon>
          <infon key="type">Increase</infon>
          <infon key="brat-type">text-bound</infon>
          <location length="9" offset="1398"/>
          <text>increased</text>
        </annotation>
        <annotation id="T25">
          <infon key="brat-id">T25</infon>
          <infon key="type">Variable</infon>
          <infon key="brat-type">text-bound</infon>
          <location length="14" offset="1408"/>
          <text>fertilizer use</text>
        </annotation>
        <annotation id="T26">
          <infon key="brat-id">T26</infon>
          <infon key="type">Decrease</infon>
          <infon key="brat-type">text-bound</infon>
          <location length="4" offset="1518"/>
          <text>less</text>
        </annotation>
        <annotation id="T27">
          <infon key="brat-id">T27</infon>
          <infon key="type">Variable</infon>
          <infon key="brat-type">text-bound</infon>
          <location length="5" offset="1523"/>
          <text>marsh</text>
        </annotation>
        <annotation id="T28">
          <infon key="brat-id">T28</infon>
          <infon key="type">Decrease</infon>
          <infon key="brat-type">text-bound</infon>
          <location length="6" offset="1542"/>
          <text>reduce</text>
        </annotation>
        <annotation id="T29">
          <infon key="brat-id">T29</infon>
          <infon key="type">Variable</infon>
          <infon key="brat-type">text-bound</infon>
          <location length="85" offset="1549"/>
          <text>the capacity of coastal regions to provide important ecological and economic services</text>
        </annotation>
        <relation id="E12">
          <infon key="brat-id">E12</infon>
          <infon key="type">Increase</infon>
          <infon key="brat-type">event</infon>
          <node refid="T22" role="Increase"/>
          <node refid="T23" role="Theme"/>
        </relation>
        <relation id="E13">
          <infon key="brat-id">E13</infon>
          <infon key="type">Increase</infon>
          <infon key="brat-type">event</infon>
          <node refid="T24" role="Increase"/>
          <node refid="T25" role="Theme"/>
        </relation>
        <relation id="E14">
          <infon key="brat-id">E14</infon>
          <infon key="type">Decrease</infon>
          <infon key="brat-type">event</infon>
          <node refid="T26" role="Decrease"/>
          <node refid="T27" role="Theme"/>
        </relation>
        <relation id="E15">
          <infon key="brat-id">E15</infon>
          <infon key="type">Decrease</infon>
          <infon key="brat-type">event</infon>
          <node refid="T28" role="Decrease"/>
          <node refid="T29" role="Theme"/>
          <node refid="E14" role="Agent"/>
        </relation>
      </sentence>
    </passage>
  </document>
</collection>
